<?xml version="1.0" encoding="UTF-8"?>
<data>
	<item id="2">
		<category>1</category>
		<title>2010哈哈美丽心世界——爱，让未来更美好！</title>
		<newsdate>2010-03-01</newsdate>
		<content><![CDATA[<p>2010年3月，炫动传播大型儿童慈善活动“2010哈哈美丽心世界——祈福世博 玩转哈哈炫方”正式拉开帷幕，活动所得以用于帮助贫困儿童实现参观世博会的梦想。</p>
		<p style="text-align:center;"><img src="/images/news/2.jpg" class="newsImage cImage"></p>
		<p>6月1日，由上海广播电视台、市慈善基金会、团市委共同主办，上海炫动传播股份有限公司承办的“爱，让未来更美好——2010哈哈美丽心世界六一儿童节特别活动”在世博园举行。活动现场展示了三千多张由小朋友们精心制作的的“世博祈福卡”，并揭晓了由千余个“哈哈炫方”搭建而成的“炫方中国馆”，寄寓孩子们对2010上海世博会的美好祝愿。此外，“哈哈美丽心世界”还特别为本次活动定制了别具意义的“哈哈世博纪念章”。儿童节当天，哈哈世博纪念章在育乐湾“哈哈少儿频道”职业体验馆正式启用，哈哈出现在现场小朋友的世博护照上，把快乐与祝福牢牢地印在孩子们的记忆中。</p>
		<p>“哈哈美丽心世界”是炫动传播于 2007年创办的大型儿童慈善品牌活动，每年定期于3月至6月举办。此外，活动更创立了“哈哈慈善基金”，借助哈哈品牌之力，通过活动募集善款，帮助有需要的孩子，并积极倡导“儿童慈善、家庭慈善、快乐慈善”的全新理念。</p>]]></content>
	</item>
</data>