<?xml version="1.0" encoding="UTF-8"?>
<data>
	<item id="31">
		<category>1</category>
		<title>炫动传播与韩国文化产业振兴院签署战略合作协议</title>
		<newsdate>2011-09-26</newsdate>
		<content><![CDATA[
			<p style="text-align:center;"><img src="/images/news/31-1.jpg" class="newsImage cImage"></p>
			<p>9月26日，炫动传播与韩国文化产业振兴院在东视大楼签署战略合作协议，为促进中韩两国动漫产业的交流发展而互相合作。双方将在动漫企业交流，动漫作品制作，专业展会活动举办，动漫主题乐园建设和拓展亚洲以及全世界的动漫市场等方面进行相互协作，共同促进专业技术和人才的交流和研究。</p>
			<p>协议签署前，双方进行了座谈。炫动传播总经理杨文艳对韩国文化产业振兴院院长李在雄一行到访表示热烈欢迎，向来宾全面介绍了公司情况。双方就相关事宜进行了深入交流和沟通，彼此对未来的合作前景充满了期待。</p>
			<p>韩国文化产业振兴院是韩国政府的文化传播机构，主要进行韩国文化的海外推介和国际文化交流合作工作。</p>
		]]></content>
	</item>
</data>