<?xml version="1.0" encoding="UTF-8"?>
<data>
	<item id="35">
		<category>1</category>
		<title><![CDATA[团中央未来网正式上线 “炫动酷地带”为其动漫频道]]></title>
		<newsdate>2011-11-07</newsdate>
		<content><![CDATA[
			<p>11月7日，经过半年多的筹备建设，属于全国广大未成年人的大型公益网站——未来网（www.k618.cn）正式开通上线。</p>
			<p>未来网以全新的创意进行构架设计，整个网站以服务未成年人快乐成长、全面发展为主线，以知识性、趣味性、思想性为内涵，根据未成年人不同年龄段的用网需求着力打造。在页面设计上，未来网创新表现形式，全部采用适合未成年人视觉特点和用网习惯的设计手法，运用游戏界面、flash、卡通、剪纸等形式，灵动活泼，具有很强的感染力。</p>
			<p style="text-align:center;"><img src="/images/news/35-1.jpg" class="newsImage cImage"><br />“炫动酷地带”作为未来网组成板块同步上线</p>
			<p>本着更好地承担社会责任，努力为未成年人健康成长作出贡献的愿望，炫动传播与“未来网”主办方团中央网络影视中心经过充分交流、沟通、磋商，达成友好合作，炫动旗下的品牌“炫动酷地带”成为“未来网”中唯一的动漫频道。作为未来网中重要的内容组成部分，该频道由炫动传播自行策划、运营，将公司这一自有品牌与未来网充分融合。</p>
			<p style="text-align:center;"><img src="/images/news/35-2.jpg" class="newsImage cImage"><br />未来网“炫动酷地带”主页</p>
			<p>炫动传播在为未来网提供动漫、教育领域提供内容的同时，依托国有全媒体优势，为未来网提供从内容到传播的一站式服务。服务内容主要包括四大板块：动漫及卡通内容的集成及编辑；炫动自有版权内容的提供；未来网全媒体传播解决方案；未来网内容衍生拓展解决方案。</p>
			<p>“炫动酷地带”先期在未来网“阳光苗圃”专区（0-6岁）、“欢乐城堡”专区（7-12岁）中上线，板块内容包括：超炫剧场、动漫新资讯、劲炫漫搜索、酷炫直播室及漫画游戏。</p>
    		<p>“炫动酷地带”强力介入未来网，此举，炫动不但能借助国家级青少年网络行为的引导和宣传平台，来进行炫动自身的品牌和内容输出，炫动品牌将通过此平台到达全国所有幼儿园和中小学，能以输出形象和内容的方式表征软实力。随着团中央在规范青少年互联网行为的进一步强化，炫动也将有机会用少于其他竞争对手的成本，进行炫动式的产业聚焦，完善自己独有的动漫产业链。</p>
    		<p>未来网凝聚着中央领导同志对广大青少年的亲切关怀，炫动传播将在团中央及中央相关部委的大力帮助支持下，根据未成年人网民对“炫动酷地带”的反馈情况，不断进行改进、完善、提升，努力为广大未成年人健康成长提供更多更好的动漫文化产品。</p>
		]]></content>
	</item>
</data>